{"name":"Chalcopyrite","desc":"Chalcopyrite ( /ˌkælkəˈpaɪraɪt, -koʊ-/ KAL-ko-PY-ryt) is a copper iron sulfide mineral that crystallizes in the tetragonal system. It has the chemical formula CuFeS2. It has a brassy to golden yellow color and a hardness of 3.5 to 4 on the Mohs scale. Its streak is diagnostic as green tinged black.","images":[{"alt":"260px","src":"//upload.wikimedia.org/wikipedia/commons/thumb/2/2c/Chalcopyrite-199453.jpg/260px-Chalcopyrite-199453.jpg"}],"link":"/wiki/Chalcopyrite"}