{"name":"Diarsenic tetraiodide","desc":"Diarsenic tetraiodide is an inorganic compound of arsenic and iodine. It is a dark red metastable solid. The compound is a closely related to the better characterized diphosphorus tetraiodide. Identified in the late 19th century with the correct empirical formula, the compound was assigned the formula (As2I4) several years later.","images":[{"alt":"Diphosphorus-tetraiodide-3D-balls.png","src":"//upload.wikimedia.org/wikipedia/commons/thumb/1/1a/Diphosphorus-tetraiodide-3D-balls.png/200px-Diphosphorus-tetraiodide-3D-balls.png"}],"link":"/wiki/Arsenic_diiodide","IUPAC name":"Arsenic diiodide","CAS Number":"13770-56-4","Chemical formula":"As<sub>2</sub>I<sub>4</sub>","Molar mass":"657.461 g/mol","Appearance":"Red crystalline solid","Melting point":"137 °C (279 °F; 410 K)","Boiling point":"380 °C (716 °F; 653 K)"}